{
    "users": [
      {
        "id" : 1,
        "name": "John Doe",
        "email": "john.doe@example.com",
        "profile_photo_url": "https://robohash.org/autfaciliset.png?size=300x300\u0026set=set1"
      },
      {
        "id" : 2,
        "name": "Jane Smith",
        "email": "jane.smith@example.com",
        "profile_photo_url":   "https://robohash.org/eiusperspiciatiseum.png?size=300x300\u0026set=set1"
      },
      {
        "id" : 3,
        "name": "Michael Johnson",
        "email": "michael.johnson@example.com",
        "profile_photo_url":   "https://robohash.org/nemoetcorrupti.png?size=300x300\u0026set=set1"
      },
      {
        "id" : 4,
        "name": "Emily Davis",
        "email": "emily.davis@example.com",
        "profile_photo_url":   "https://robohash.org/rationenobisqui.png?size=300x300\u0026set=set1"
      },
      {
        "id" : 5,
        "name": "Robert Brown",
        "email": "robert.brown@example.com",
        "profile_photo_url":  "https://robohash.org/nihilnumquammolestiae.png?size=300x300\u0026set=set1"
      },
      {
        "id" : 6,
        "name": "Amanda White",
        "email": "amanda.white@example.com",
        "profile_photo_url":   "https://robohash.org/nemoaliaseum.png?size=300x300\u0026set=set1"
      },
      {
        "id" : 7,
        "name": "Daniel Lee",
        "email": "daniel.lee@example.com",
        "profile_photo_url":   "https://robohash.org/quivoluptateminus.png?size=300x300\u0026set=set1"
      },
      {
        "id" : 8,
        "name": "Olivia Taylor",
        "email": "olivia.taylor@example.com",
        "profile_photo_url":   "https://robohash.org/molestiasnecessitatibusaliquam.png?size=300x300\u0026set=set1"
      },
      {
        "id" : 9,
        "name": "William Clark",
        "email": "william.clark@example.com",
        "profile_photo_url":   "https://robohash.org/utcupiditateillo.png?size=300x300\u0026set=set1"
      },
      {
        "id" : 10,
        "name": "Sophia Anderson",
        "email": "sophia.anderson@example.com",
        "profile_photo_url":  "https://robohash.org/temporarepellendushic.png?size=300x300\u0026set=set1"
      }
    ]
  }
  

 